glass_engine/AffineTransform.py
glass_engine/Background.py
glass_engine/BasicScene.py
glass_engine/Camera.py
glass_engine/ColorMap.py
glass_engine/Fog.py
glass_engine/Frame.py
glass_engine/GlassEngineConfig.py
glass_engine/LICENSE
glass_engine/Material.py
glass_engine/Mesh.py
glass_engine/Model.py
glass_engine/Scene.py
glass_engine/SceneNode.py
glass_engine/SkyBox.py
glass_engine/SkyDome.py
glass_engine/SlideAverageFilter.py
glass_engine/VideoRecorder.py
glass_engine/WeightedIntegrator.py
glass_engine/__init__.py
glass_engine/algorithm.py
glass_engine/callback_vec.py
glass_engine/lut.py
glass_engine/Animations/Animation.py
glass_engine/Animations/AnimationGroup.py
glass_engine/Animations/Chronoscope.py
glass_engine/Animations/EasingCurve.py
glass_engine/Animations/ParallelAnimation.py
glass_engine/Animations/SequentialAnimation.py
glass_engine/Animations/__init__.py
glass_engine/Geometries/Box.py
glass_engine/Geometries/Circle.py
glass_engine/Geometries/CircleFace.py
glass_engine/Geometries/Cone.py
glass_engine/Geometries/ConeSide.py
glass_engine/Geometries/ConeTrustum.py
glass_engine/Geometries/ConeTrustumSide.py
glass_engine/Geometries/CoordSys.py
glass_engine/Geometries/Cylinder.py
glass_engine/Geometries/CylinderSide.py
glass_engine/Geometries/CylindricalFSurf.py
glass_engine/Geometries/Dodecahedron.py
glass_engine/Geometries/EllipseFace.py
glass_engine/Geometries/Extruder.py
glass_engine/Geometries/FSurf.py
glass_engine/Geometries/Floor.py
glass_engine/Geometries/Hexahedron.py
glass_engine/Geometries/HollowRPolygonFace.py
glass_engine/Geometries/Icosahedron.py
glass_engine/Geometries/Icosphere.py
glass_engine/Geometries/ImageQuad.py
glass_engine/Geometries/Octahedron.py
glass_engine/Geometries/Point.py
glass_engine/Geometries/Points.py
glass_engine/Geometries/Polyline.py
glass_engine/Geometries/Prism.py
glass_engine/Geometries/PrismSide.py
glass_engine/Geometries/Pyramid.py
glass_engine/Geometries/PyramidSide.py
glass_engine/Geometries/PyramidTrustum.py
glass_engine-0.1.64.dist-info/licenses/LICENSE
glass_engine-0.1.64.dist-info/METADATA
glass_engine-0.1.64.dist-info/WHEEL
glass_engine-0.1.64.dist-info/entry_points.txt
glass_engine-0.1.64.dist-info/top_level.txt
glass_engine-0.1.64.dist-info/RECORD
