Metadata-Version: 2.4
Name: glass_engine
Version: 0.1.64
Summary: An easy-to-use 3D rendering engine for Python
Home-page: https://github.com/Time-Coder/Glass-Engine
Author: 王炳辉 (BingHui-WANG)
Author-email: binghui.wang@foxmail.com
Classifier: Programming Language :: Python :: 3
Classifier: License :: OSI Approved :: MIT License
Classifier: Operating System :: OS Independent
Requires-Python: >=3.7
License-File: LICENSE
Requires-Dist: python-glass==0.1.64
Requires-Dist: assimpy>=5.4.3.3
Requires-Dist: pytweening
Dynamic: author
Dynamic: author-email
Dynamic: classifier
Dynamic: description
Dynamic: description-content-type
Dynamic: home-page
Dynamic: license-file
Dynamic: requires-dist
Dynamic: requires-python
Dynamic: summary
